{
  "id": "4",
  "img": "https://github.com/Alex-Smyslov/NR-Fish-React/blob/main/public/product/product4.jpg?raw=true",
  "title": "Удилище фидерное Flagman Cast Master Feeder Heavy 3,9м 150гр",
  "description": "При создании этой серии эксперты нашей компании поставили себе задачу - достичь высокого качества и при этом обеспечить доступность для широкого круга рыболовов. И эта задача была решена блестяще. Новые удилища отличаются высокой чувствительностью, вязкостью, прекрасными бросковыми данными. Данная модель – отличный вариант для больших рек и водохранилищ. С одной стороны, она позволяет далеко и точно забрасывать тяжелые кормушки, с другой – обладает маневренностью, необходимой для скоростной ловли. Кроме того, это удилище пригодится для ловли карпа на коммерческих водоемах с помощью кормушек The Method. Будучи достаточно жестким и очень мощным, это удилище имеет прекрасный баланс, благодаря чему им можно долго ловить, не утомляясь. При вываживании прекрасно чувствуется даже некрупная рыба, что позволяет его полностью контролировать, а во время борьбы с настоящим трофеем бланк, изгибаясь практически по всей длине, великолепно парирует его рывки. Комфортная дистанция ловли составляет 20–50 м, оптимальный вес кормушек – 40–90 г. Комплектуется тремя вершинами с посадочным диаметром 2,7.",
  "price": "6197",
  "rating": "3,5"
}
